win32_setfiletime.py
win32_setfiletime-1.0.0.dist-info/LICENSE
win32_setfiletime-1.0.0.dist-info/METADATA
win32_setfiletime-1.0.0.dist-info/WHEEL
win32_setfiletime-1.0.0.dist-info/top_level.txt
win32_setfiletime-1.0.0.dist-info/RECORD
